[{"title": "The Philippine republic v.1 1926", "author": "Tavenner, Clyde H. (Clyde Howard), 1882-1942.", "id": "000496371"}, {"title": "The Philippine republic v.2 1926", "author": "Tavenner, Clyde H. (Clyde Howard), 1882-1942.", "id": "000496371"}, {"title": "The Philippine republic v.3 1926", "author": "Tavenner, Clyde H. (Clyde Howard), 1882-1942.", "id": "000496371"}, {"title": "The Philippine republic v.4 1926", "author": "Tavenner, Clyde H. (Clyde Howard), 1882-1942.", "id": "000496371"}, {"title": "The Philippine republic v.5 1926", "author": "Tavenner, Clyde H. (Clyde Howard), 1882-1942.", "id": "000496371"}, {"title": "The Philippine republic v.6 1926", "author": "Tavenner, Clyde H. (Clyde Howard), 1882-1942.", "id": "000496371"}, {"title": "The Philippine republic v.7 1926", "author": "Tavenner, Clyde H. (Clyde Howard), 1882-1942.", "id": "000496371"}, {"title": "The Philippine republic v.8 1926", "author": "Tavenner, Clyde H. (Clyde Howard), 1882-1942.", "id": "000496371"}, {"title": "The Philippine republic v.9 1926", "author": "Tavenner, Clyde H. (Clyde Howard), 1882-1942.", "id": "000496371"}, {"title": "The Philippine republic v.10 1926", "author": "Tavenner, Clyde H. (Clyde Howard), 1882-1942.", "id": "000496371"}, {"title": "The Philippine republic v.11 1926", "author": "Tavenner, Clyde H. (Clyde Howard), 1882-1942.", "id": "000496371"}, {"title": "Die Philippinen : ein kulturgeographischer R\u00fcck- und Ausblick von Walther Tuckermann ", "author": "Tuckermann, Walther, 1880-", "id": "002190224"}, {"title": "Die Philippinen : ein kulturgeographischer R\u00fcck- und Ausblick von Walther Tuckermann ", "author": "Tuckermann, Walther, 1880-", "id": "002190224"}, {"title": "Die Philippinen : ein kulturgeographischer R\u00fcck- und Ausblick von Walther Tuckermann ", "author": "Tuckermann, Walther, 1880-", "id": "002190224"}, {"title": "Through the Philippines and Hawaii by Frank G. Carpenter ... with more than 100 illustrations from original photographs ", "author": "Carpenter, Frank G. 1855-1924.", "id": "001870976"}, {"title": "Through the Philippines and Hawaii by Frank G. Carpenter ... with more than 100 illustrations from original photographs ", "author": "Carpenter, Frank G. 1855-1924.", "id": "001870976"}]