[{"title": "Le califat, son e\u0301volution vers une socie\u0301te\u0301 des nations orientale par A. Sanhoury ... pre\u0301face de Edouard Lambert ", "author": "Sanhu\u0304ri\u0304, \u02bbAbd al-Razza\u0304q Ah\u0323mad, 1895-1971.", "id": "001661029"}, {"title": "Le califat, son e\u0301volution vers une socie\u0301te\u0301 des nations orientale par A. Sanhoury ... pre\u0301face de Edouard Lambert ", "author": "Sanhu\u0304ri\u0304, \u02bbAbd al-Razza\u0304q Ah\u0323mad, 1895-1971.", "id": "001661029"}, {"title": "Das chalifat von Rudolf Tschudi ... ", "author": "Tschudi, Rudolf, 1884-1960.", "id": "002092230"}, {"title": "Der Islam v.14-15 1925-1926", "author": "", "id": "000525208"}, {"title": "Lubb al-t\u0101rikh ", "author": "Bahib, Muhammad", "id": "001862386"}, {"title": "The Moslem World v.16 (1926)", "author": "Zwemer, Samuel Marinus, 1867-1952 Hartford Seminary Foundation Christian Literature Society for India", "id": "006665172"}, {"title": "Les penseurs de l'Islam v.1", "author": "Carra de Vaux, Bernard, baron, b. 1867.", "id": "001240437"}, {"title": "Les penseurs de l'Islam v. 1-2", "author": "Carra de Vaux, Bernard, baron, b. 1867.", "id": "001240437"}, {"title": "Les penseurs de l'Islam v.2", "author": "Carra de Vaux, Bernard, baron, b. 1867.", "id": "001240437"}, {"title": "Les penseurs de l'Islam v.3", "author": "Carra de Vaux, Bernard, baron, b. 1867.", "id": "001240437"}, {"title": "Les penseurs de l'Islam v. 3", "author": "Carra de Vaux, Bernard, baron, b. 1867.", "id": "001240437"}, {"title": "Les penseurs de l'Islam v.4", "author": "Carra de Vaux, Bernard, baron, b. 1867.", "id": "001240437"}, {"title": "Les penseurs de l'Islam v. 4", "author": "Carra de Vaux, Bernard, baron, b. 1867.", "id": "001240437"}, {"title": "Les penseurs de l'Islam v.5", "author": "Carra de Vaux, Bernard, baron, b. 1867.", "id": "001240437"}, {"title": "Les penseurs de l'Islam 10516", "author": "Carra de Vaux, Bernard, baron, b. 1867.", "id": "001240437"}, {"title": "Les penseurs de l'Islam 10517", "author": "Carra de Vaux, Bernard, baron, b. 1867.", "id": "001240437"}, {"title": "Les penseurs de l'Islam 10518", "author": "Carra de Vaux, Bernard, baron, b. 1867.", "id": "001240437"}, {"title": "Les penseurs de l'Islam 10519", "author": "Carra de Vaux, Bernard, baron, b. 1867.", "id": "001240437"}, {"title": "Les penseurs de l'Islam 10520", "author": "Carra de Vaux, Bernard, baron, b. 1867.", "id": "001240437"}, {"title": "Revue du monde musulman v.1", "author": "Mission scientifique du Maroc.", "id": "000521273"}, {"title": "Revue du monde musulman v.3", "author": "Mission scientifique du Maroc.", "id": "000521273"}, {"title": "Revue du monde musulman v.4", "author": "Mission scientifique du Maroc.", "id": "000521273"}, {"title": "Revue du monde musulman v.5", "author": "Mission scientifique du Maroc.", "id": "000521273"}, {"title": "Revue du monde musulman v.6", "author": "Mission scientifique du Maroc.", "id": "000521273"}, {"title": "Revue du monde musulman v.8", "author": "Mission scientifique du Maroc.", "id": "000521273"}, {"title": "Revue du monde musulman v.9", "author": "Mission scientifique du Maroc.", "id": "000521273"}, {"title": "Revue du monde musulman v.13", "author": "Mission scientifique du Maroc.", "id": "000521273"}, {"title": "Revue du monde musulman v.14", "author": "Mission scientifique du Maroc.", "id": "000521273"}, {"title": "Revue du monde musulman v.15", "author": "Mission scientifique du Maroc.", "id": "000521273"}, {"title": "Revue du monde musulman v.16", "author": "Mission scientifique du Maroc.", "id": "000521273"}, {"title": "Revue du monde musulman v.17", "author": "Mission scientifique du Maroc.", "id": "000521273"}, {"title": "Revue du monde musulman v.17 (Index v.1-16)", "author": "Mission scientifique du Maroc.", "id": "000521273"}, {"title": "Revue du monde musulman v.18", "author": "Mission scientifique du Maroc.", "id": "000521273"}, {"title": "Revue du monde musulman v.19", "author": "Mission scientifique du Maroc.", "id": "000521273"}, {"title": "Revue du monde musulman v.20", "author": "Mission scientifique du Maroc.", "id": "000521273"}, {"title": "Revue du monde musulman v.21", "author": "Mission scientifique du Maroc.", "id": "000521273"}, {"title": "Revue du monde musulman v.22", "author": "Mission scientifique du Maroc.", "id": "000521273"}, {"title": "Revue du monde musulman v.23", "author": "Mission scientifique du Maroc.", "id": "000521273"}, {"title": "Revue du monde musulman v.24", "author": "Mission scientifique du Maroc.", "id": "000521273"}, {"title": "Revue du monde musulman v.24", "author": "Mission scientifique du Maroc.", "id": "000521273"}, {"title": "Revue du monde musulman v.25", "author": "Mission scientifique du Maroc.", "id": "000521273"}, {"title": "Revue du monde musulman v.26", "author": "Mission scientifique du Maroc.", "id": "000521273"}, {"title": "Revue du monde musulman v.27", "author": "Mission scientifique du Maroc.", "id": "000521273"}, {"title": "Revue du monde musulman v.28", "author": "Mission scientifique du Maroc.", "id": "000521273"}, {"title": "Revue du monde musulman v.29", "author": "Mission scientifique du Maroc.", "id": "000521273"}, {"title": "Revue du monde musulman v.29", "author": "Mission scientifique du Maroc.", "id": "000521273"}, {"title": "Revue du monde musulman v.30", "author": "Mission scientifique du Maroc.", "id": "000521273"}, {"title": "Revue du monde musulman v.31", "author": "Mission scientifique du Maroc.", "id": "000521273"}, {"title": "Revue du monde musulman v.32", "author": "Mission scientifique du Maroc.", "id": "000521273"}, {"title": "Revue du monde musulman v.33", "author": "Mission scientifique du Maroc.", "id": "000521273"}, {"title": "Revue du monde musulman v.34", "author": "Mission scientifique du Maroc.", "id": "000521273"}, {"title": "Revue du monde musulman v.34-35", "author": "Mission scientifique du Maroc.", "id": "000521273"}, {"title": "Revue du monde musulman v.35", "author": "Mission scientifique du Maroc.", "id": "000521273"}, {"title": "Revue du monde musulman v.35-36", "author": "Mission scientifique du Maroc.", "id": "000521273"}, {"title": "Revue du monde musulman v.36", "author": "Mission scientifique du Maroc.", "id": "000521273"}, {"title": "Revue du monde musulman v.37", "author": "Mission scientifique du Maroc.", "id": "000521273"}, {"title": "Revue du monde musulman v.38", "author": "Mission scientifique du Maroc.", "id": "000521273"}, {"title": "Revue du monde musulman v.38", "author": "Mission scientifique du Maroc.", "id": "000521273"}, {"title": "Revue du monde musulman v.39", "author": "Mission scientifique du Maroc.", "id": "000521273"}, {"title": "Revue du monde musulman v.40-41", "author": "Mission scientifique du Maroc.", "id": "000521273"}, {"title": "Revue du monde musulman v.40-42", "author": "Mission scientifique du Maroc.", "id": "000521273"}, {"title": "Revue du monde musulman v.42", "author": "Mission scientifique du Maroc.", "id": "000521273"}, {"title": "Revue du monde musulman v.43", "author": "Mission scientifique du Maroc.", "id": "000521273"}, {"title": "Revue du monde musulman v.44-45", "author": "Mission scientifique du Maroc.", "id": "000521273"}, {"title": "Revue du monde musulman v.46", "author": "Mission scientifique du Maroc.", "id": "000521273"}, {"title": "Revue du monde musulman v.46-48", "author": "Mission scientifique du Maroc.", "id": "000521273"}, {"title": "Revue du monde musulman v.47", "author": "Mission scientifique du Maroc.", "id": "000521273"}, {"title": "Revue du monde musulman v.47", "author": "Mission scientifique du Maroc.", "id": "000521273"}, {"title": "Revue du monde musulman v.48-50", "author": "Mission scientifique du Maroc.", "id": "000521273"}, {"title": "Revue du monde musulman v.49-50", "author": "Mission scientifique du Maroc.", "id": "000521273"}, {"title": "Revue du monde musulman v.51", "author": "Mission scientifique du Maroc.", "id": "000521273"}, {"title": "Revue du monde musulman v.52", "author": "Mission scientifique du Maroc.", "id": "000521273"}, {"title": "Revue du monde musulman v.52", "author": "Mission scientifique du Maroc.", "id": "000521273"}, {"title": "Revue du monde musulman v.53", "author": "Mission scientifique du Maroc.", "id": "000521273"}, {"title": "Revue du monde musulman v.55-56", "author": "Mission scientifique du Maroc.", "id": "000521273"}, {"title": "Revue du monde musulman v.56", "author": "Mission scientifique du Maroc.", "id": "000521273"}, {"title": "Revue du monde musulman v.61-63 1925-1926", "author": "Mission scientifique du Maroc.", "id": "000521273"}, {"title": "Revue du monde musulman v.62-66 (1925-26)", "author": "Mission scientifique du Maroc.", "id": "000521273"}, {"title": "Revue du monde musulman v.63-66 (Includes Index v.1-66)", "author": "Mission scientifique du Maroc.", "id": "000521273"}, {"title": "Revue du monde musulman v.64", "author": "Mission scientifique du Maroc.", "id": "000521273"}, {"title": "Revue du monde musulman v.65-66 1902-1926 Index", "author": "Mission scientifique du Maroc.", "id": "000521273"}]