[{"title": "The American political science review v.1-20 1906-1926 Index", "author": "Ogg, Frederic Austin, 1878-1956, Fairlie, John A. (John Archibald), 1872-1947, Willoughby, Westel Woodbury, 1867-1945, American Political Science Association.", "id": "000518685"}, {"title": "The American political science review v.20 (1926)", "author": "Ogg, Frederic Austin, 1878-1956, Fairlie, John A. (John Archibald), 1872-1947, Willoughby, Westel Woodbury, 1867-1945, American Political Science Association.", "id": "000518685"}, {"title": "L'Anne\u0301e politique, e\u0301conomique et coope\u0301rative, Revue des e\u0301tudes coope\u0301ratives, Res publica. nouv v.5:no.17-20 1925-26", "author": "", "id": "007848129"}, {"title": "Antirevolutionaire staatkunde v.2 1926", "author": "Kuyper, Abraham, 1837-1920. Studie der Antirevolutionaire Beginselen. Dr. Abraham Kuyperstichting.", "id": "000524749"}, {"title": "Archiv des \u00f6ffentlichen Rechts n.s. 9-10 1925-1926", "author": "", "id": "000521425"}, {"title": "Politica v.24 1926", "author": "", "id": "000496504"}, {"title": "Politica v.24(1926)", "author": "", "id": "007912604"}, {"title": "Politica v. 25 1926", "author": "", "id": "000496504"}, {"title": "Politica v.25(1926)", "author": "", "id": "007912604"}, {"title": "Politica v.26 1926", "author": "", "id": "000496504"}, {"title": "Politica v.26(1926)", "author": "", "id": "007912604"}, {"title": "Public administration : an international quarterly v.4 1926", "author": "OCLC FirstSearch Electronic Collections Online. Royal Institute of Public Administration. Institute of Public Administration (Great Britain)", "id": "000505386"}, {"title": "Public administration v.4 1926", "author": "Institute of Public Administration (Great Britain) Royal Institute of Public Administration.", "id": "006302336"}, {"title": "Public administration v.4 1926", "author": "Institute of Public Administration (Great Britain) Royal Institute of Public Administration.", "id": "006302336"}, {"title": "Revue du droit public et de la science politique en France et \u00e0 l'\u00e9tranger v.43 1926", "author": "Larnaude, Ferdinand, 1853-1942.", "id": "004292344"}, {"title": "Revue du droit public et de la science politique en France et \u00e0 l'\u00e9tranger v. 43 1926", "author": "Larnaude, Ferdinand, 1853-1942.", "id": "004292344"}, {"title": "Revue g\u00e9n\u00e9rale d'administration 1926", "author": "France. Minist\u00e8re de l'int\u00e9rieur", "id": "000530600"}, {"title": "Science(s) politique(s). v.49(1926)", "author": "Universite\u0301 de Paris VIII-Vincennes a\u0300 Saint-Denis. De\u0301partement de science politique.", "id": "011451778"}, {"title": "Zeitschrift f\u00fcr Politik v. 15 1925-26", "author": "Grabowsky, Adolf, 1880-1969. Schmidt, Richard, 1862-1944. Hochschule f\u00fcr Politik M\u00fcnchen.", "id": "000597562"}, {"title": "Zeitschrift f\u00fcr Politik v.15 1925-1926", "author": "Grabowsky, Adolf, 1880-1969. Schmidt, Richard, 1862-1944. Hochschule f\u00fcr Politik M\u00fcnchen.", "id": "000597562"}]