[{"title": "Annales de la Socie\u0301te\u0301 arche\u0301ologique de l'arrondissement de Nivelles v.011 yr.1926", "author": "Socie\u0301te\u0301 arche\u0301ologique de l'arrondissement de Nivelles.", "id": "100422385"}, {"title": "Annales v.33-35 1923-1926", "author": "Comite\u0301 flamand de France, Lille.", "id": "002129683"}, {"title": "Antwerpsch archievenblad uitg. op last van het gemeentebestuur ser.2 v.1 (1926)", "author": "Antwerp (Belgium) Archief.", "id": "000678769"}, {"title": "Bruges and its past by Malcolm Letts ; with 13 illustrations and a sketch map ", "author": "Letts, Malcolm, 1882-1957.", "id": "001833755"}, {"title": "Bruges and its past by Malcolm Letts ; with 13 illustrations and a sketch map ", "author": "Letts, Malcolm, 1882-1957.", "id": "001833755"}, {"title": "Pendant l'\u00e9migration ", "author": "[Adseux, Quirin d'], 1743-1821.", "id": "001636114"}, {"title": "The story of Bruges by Ernest Gilliat-Smith. Illustrated by Edith Calvert and Herbert Railton ", "author": "Gilliat-Smith, Ernest.", "id": "102069265"}]