[{"title": "Buccaneers and pirates of our coasts [by] Frank R. Stockton ", "author": "Stockton, Frank R., 1834-1902", "id": "102001762"}, {"title": "The History of the lives and bloody exploits of the most noted pirates : their trials and executions Including a correct account of the late piracies committed in the West Indies, and the expedition of Commodore Porter; also, those committed on the brig Mexican, who were tried and executed at Boston, in 1835 : embellished with engravings from original designs ", "author": "", "id": "005056462"}]