[{"title": "The adventures of Don Quixote ", "author": "Cervantes Saavedra, Miguel de, 1547-1616.", "id": "101867921"}, {"title": "Algunas noticias nuevas acerca de Rodrigo Cota ", "author": "Cotarelo y Mori, Emilio, 1857-1936.", "id": "001522502"}, {"title": "Algunas noticias nuevas acerca de Rodrigo Cota ", "author": "Cotarelo y Mori, Emilio, 1857-1936.", "id": "001522502"}, {"title": "Antonio de Guevara : [I] Sa vie. [II] Son oeuvre ", "author": "Costes, Rene\u0301.", "id": "007972034"}, {"title": "Baltasar Graci\u00e1n; escritor aragon\u00e9s del siglo XVIII Curso monogr\u00e1fico celebrado en la Universidad Literaria de Zaragoza ... y ahora impreso a expensas de la Excma. Diputaci\u00f3n provincial de esta ciudad, que profesaron Salvador Minguij\u00f3n [et al.] ", "author": "Universidad de Zaragoza.", "id": "009964324"}, {"title": "Calderon und das Wesen des katholischen Dramas eine a\u0308sthetisch-dogmatische Untersuchung von Dr. Phil. Hermann Weisser ", "author": "Weisser, Hermann.", "id": "006581291"}, {"title": "Cervantes Traducci\u00f3n por Margarita Nelken y un retrato del autor por Picasso ", "author": "Faure, \u00c9lie, 1873-1937.", "id": "001518391"}, {"title": "The choice humorous and satirical works Quevedo ; translated into English by Sir Roger L'Estrange, John Stevens, and others ; rev. and edited, with an introd., notes, and a version of The life of the great rascal (Vida del Busc\u00f3n) by Charles Duff ", "author": "Quevedo, Francisco de, 1580-1645.", "id": "001053363"}, {"title": "The choice humorous and satirical works Quevedo ; translated into English by Sir Roger L'Estrange, John Stevens, and others ; rev. and edited, with an introd., notes, and a version of The life of the great rascal (Vida del Busc\u00f3n) by Charles Duff ", "author": "Quevedo, Francisco de, 1580-1645.", "id": "001053363"}, {"title": "Comedia famosa de Amar sin saber a qui\u00e9n de Lope de Vega Carpio ed., with notes and vocabulary, by Milton A. Buchanan ... and Bernard Franzen-Swedelius ... ", "author": "Vega, Lope de, 1562-1635.", "id": "001721510"}, {"title": "La criminologi\u0301a de El Quijote : notas para un estudio [por] Quintiliano Saldan\u0303a ", "author": "Saldan\u0303a, Quintiliano, 1878-1938.", "id": "007030124"}, {"title": "Descripci\u00f3n de una fiesta de toros y ca\u00f1as que celebr\u00f3 la Maestranza de Caballer\u00eda de Sevilla, el a\u00f1o 1671 Prec\u00e9dela un estudio biogr\u00e1fico-cr\u00edtico, por Santiago Montoto ", "author": "Cepeda y Guzm\u00e1n, Carlos Alberto, 1640-1692.", "id": "001523816"}, {"title": "Don Kishot : ish Lamansha li-Migu\u02bcel Di Servantes ; targum mekutsar, [\u1e24.N. Byalik]. \u05d3\u05d5\u05df \u05e7\u05d9\u05e9\u05d5\u05d8 : \u05d0\u05d9\u05e9 \u05dc\u05de\u05e0\u05e9\u05d0\u05dc\u05de\u05d9\u05d2\u05d5\u05d0\u05dc \u05d3\u05d9 \u05e1\u05e8\u05d5\u05d5\u05e0\u05d8\u05e1 ; \u05ea\u05e8\u05d2\u05d5\u05dd \u05de\u05e7\u05d5\u05e6\u05e8, [\u05d7. \u05e0. \u05d1\u05d9\u05d0\u05dc\u05d9\u05e7]. ", "author": "Cervantes Saavedra, Miguel de, 1547-1616 \u05e1\u05e8\u05d5\u05e0\u05d8\u05e1 \u05e1\u05d5\u05d3\u05e8\u05d4, \u05de\u05d9\u05d2\u05dc \u05d3\u05d4, 1547-1616.", "id": "002242562"}, {"title": "Don Quijote, Don Juan y la Celestina; ensayos de simpat\u00eda ", "author": "Maeztu, Ramiro de, 1875-1936.", "id": "001048608"}, {"title": "Don Quijote, Don Juan y la Celestina; ensayos de simpat\u00eda ", "author": "Maeztu, Ramiro de, 1875-1936.", "id": "001048608"}, {"title": "Don Quijote, Don Juan y la Celestina; ensayos de simpat\u00eda ", "author": "Maeztu, Ramiro de, 1875-1936.", "id": "001048608"}, {"title": "Drei Zwischenspiele, herausgegeben von Ludwig Pfandl ", "author": "Cervantes Saavedra, Miguel de, 1547-1616.", "id": "008368799"}, {"title": "Escritores americanos celebrados por Cervantes en el Canto de Cali\u0301ope ", "author": "Medina, Jose\u0301 Toribio, 1852-1930.", "id": "006660833"}, {"title": "Gu\u00eda del lector del \"Quijote\" ", "author": "Madariaga, Salvador de, 1886-1978.", "id": "001111653"}, {"title": "Gu\u00eda del lector del \"Quijote\" ", "author": "Madariaga, Salvador de, 1886-1978.", "id": "001111653"}, {"title": "A Hebrew version of Don Quijote by H. Chonon Berkowitz ", "author": "Berkowitz, H. Chonon, 1895-1945.", "id": "008368813"}, {"title": "L'inge\u0301nieux hidalgo Miguel Cervantes [par] Han Ryner ", "author": "Ryner, Han, 1861-1938.", "id": "006532363"}, {"title": "El ingrato agradecido by Juan de Matos Fragoso ; edited from the manuscript in the Biblioteca nacional by Harry Clifton Heaton ", "author": "Matos Fragoso, Juan de, 1608-1688.", "id": "001220629"}, {"title": "Luis de Gongora y Argote (1561-1627) by Clara Louisa Penney ... ", "author": "Penney, Clara Louisa.", "id": "001807830"}, {"title": "Miguel de Cervantes : su vida gloriosa por Mari\u0301a Luz Morales ", "author": "Morales, Mari\u0301a Luz.", "id": "006532362"}, {"title": "Las paredes oyen por Juan Ruiz de Alarc\u00f3n y Mendoza; ed., with introdu Caroline B. Bourland ... ", "author": "Ruiz de Alarc\u00f3n, Juan, 1580?-1639.", "id": "001523434"}, {"title": "The pleasant history of Lazarillo de Tormes, his fortunes and adversities, containing the strange adventures that befell him in the service of sundry masters as written supposedly by Diego Hurtado de Mendoza; together with the pursuit or second part of his life, as related by Juan de Luna; with a general introduction to the Rogues' bookshelf, by Carl Van Doren ", "author": "", "id": "001590758"}, {"title": "El \"Quijote\" y los libros de caballer\u00edas ", "author": "Guzm\u00e1n, Eugenio.", "id": "001037328"}, {"title": "El \"Quijote\" y los libros de caballer\u00edas ", "author": "Guzm\u00e1n, Eugenio.", "id": "001037328"}, {"title": "El \"Quijote\" y los libros de caballeri\u0301as ", "author": "Guzma\u0301n, Eugenio.", "id": "102628863"}, {"title": "O romance de Amadis. Reconstitui\u00e7\u00e3o do Amadis de Gaula dos Lobeiras (sec. XIII-XIV) por Affonso Lopes Vieira ", "author": "Vasconcellos, Carolina Micha\u00eblis de, 1851-1925. Lopes Vieira, Afonso, 1878-1946.", "id": "007112786"}, {"title": "O romance de Amadis. Reconstitui\u00e7\u00e3o do Amadis de Gaula dos Lobeiras (sec. XIII-XIV) por Affonso Lopes Vieira ", "author": "Vasconcellos, Carolina Micha\u00eblis de, 1851-1925. Lopes Vieira, Afonso, 1878-1946.", "id": "007112786"}, {"title": "Teatro selecto: comedias y pasos ", "author": "Rueda, Lope de, -1565.", "id": "001523258"}, {"title": "Teatro seleccio\u0301n hecha por Jose\u0301 Vallejo ", "author": "Ruiz de Alarco\u0301n, Juan, 1580?-1639.", "id": "006532339"}, {"title": "Teatro Pr\u00f3logo, edici\u00f3n y notas de Angel Valbuena Prat v.1", "author": "Mira de Amescua, Antonio, -1644", "id": "000908299"}, {"title": "Teatro Pr\u00f3logo, edici\u00f3n y notas de Angel Valbuena Prat v. 1", "author": "Mira de Amescua, Antonio, -1644", "id": "000908299"}, {"title": "Teatro Pr\u00f3logo, edici\u00f3n y notas de Angel Valbuena Prat v.1 1926", "author": "Mira de Amescua, Antonio, -1644", "id": "000908299"}, {"title": "Teatro Pr\u00f3logo, edici\u00f3n y notas de Angel Valbuena Prat v.2", "author": "Mira de Amescua, Antonio, -1644", "id": "000908299"}, {"title": "Teatro Pr\u00f3logo, edici\u00f3n y notas de Angel Valbuena Prat v. 2", "author": "Mira de Amescua, Antonio, -1644", "id": "000908299"}, {"title": "Teatro Pr\u00f3logo, edici\u00f3n y notas de Angel Valbuena Prat v.2 1928", "author": "Mira de Amescua, Antonio, -1644", "id": "000908299"}, {"title": "Teatro Pr\u00f3logo, edici\u00f3n y notas de Angel Valbuena Prat v.82", "author": "Mira de Amescua, Antonio, -1644", "id": "000908299"}, {"title": "Teatro Pr\u00f3logo, edici\u00f3n y notas de Angel Valbuena Prat v.171", "author": "Mira de Amescua, Antonio, -1644", "id": "000908299"}, {"title": "Three plays by Caldero\u0301n ... edited, with introduction and notes, by George Tyler Northup ... ", "author": "Caldero\u0301n de la Barca, Pedro, 1600-1681.", "id": "001050267"}, {"title": "Three plays by Caldero\u0301n ... edited, with introduction and notes, by George Tyler Northup ... ", "author": "Caldero\u0301n de la Barca, Pedro, 1600-1681.", "id": "001050267"}, {"title": "Tragedia de Mirrha ", "author": "Villalo\u0301n, Cristo\u0301bal de, 16th cent.", "id": "008369794"}, {"title": "La tragedia por los celos : comedia famosa de Don Guill\u00e9n de Castro y Bellvis / edited after a 17th century suelta, with an introduction, variants, and notes by Hymen Alpern ", "author": "Castro, Guill\u00e9n de, 1569-1631.", "id": "001050490"}, {"title": "La tragedia por los celos : comedia famosa de Don Guill\u00e9n de Castro y Bellvis / edited after a 17th century suelta, with an introduction, variants, and notes by Hymen Alpern ", "author": "Castro, Guill\u00e9n de, 1569-1631.", "id": "001050490"}, {"title": "La tragedia por los celos : comedia famosa de Don Guille\u0301n de Castro y Bellvis ; edited after a 17th century suelta, with an introduction, variants, and notes, by Hymen Alpern ", "author": "Castro, Guille\u0301n de, 1569-1631.", "id": "008368702"}]