[{"title": "Art for all : a course of drawing, composition and design by J. Littlejohns V.2", "author": "Littlejohns, J. 1874-1955", "id": "101884330"}, {"title": "Beachreibendes Verzeichnis der Basler Handzeichnungen des Urs Graf. : Nebat einem Katalog der Basler Urs-Graf Ausstellung, l. Juli bis 15. September 1926. Hrsg. im Auftrag der Kommission f\u00fcr die Oeffentliche Kunstaammlung in Basel ", "author": "Koegler, Hans.", "id": "001982364"}, {"title": "Dessins anciens, collections cte.de Robiano; vente aux ench\u00e8res publiques les 15 et juin 1926 Direction: Ant. W.M. Mensing ", "author": "Frederik Muller &amp; Cie.", "id": "001982159"}, {"title": "Dibujos del Instituto de Gij\u00f3n ", "author": "Moreno Villa, Jos\u00e9, 1887-1955.", "id": "001482675"}, {"title": "Dibujos del Instituto de Gij\u00f3n ", "author": "Moreno Villa, Jos\u00e9, 1887-1955.", "id": "001482675"}, {"title": "Drawings of the early Flemish school ", "author": "Popham, A. E. 1889-1970.", "id": "001469060"}, {"title": "Dutch drawings of the seventeenth century by J.H.J. Mellaart ", "author": "Mellaart, J.H.J.", "id": "001469191"}, {"title": "The elements of dynamic symmetry by Jay Hambidge ... ", "author": "Hambidge, Jay, 1867-1924.", "id": "001468758"}, {"title": "Figure sketching by Bernice Oehler ", "author": "Oehler, Bernice Olivia, 1881-", "id": "100820476"}, {"title": "Figure sketching by Bernice Oehler ", "author": "Oehler, Bernice Olivia, b. 1881.", "id": "007033995"}, {"title": "Flemish drawings of the seventeenth century by T.W. Muchall-Viebrook ; with seventy illustrations in collotype ", "author": "Muchall-Viebrook, Thomas W        , 1881-", "id": "005834758"}, {"title": "Florentine drawings of the quattrocento ", "author": "Ede, H. S. 1895-1990.", "id": "001482709"}, {"title": "Freehand and perspective drawing : a practical treatise on the principles of artistic perception and the art of correct graphic delineation ", "author": "Lawrence, William Henry, b. 1868. Everett, Herbert Edward, 1863-1932. American Technical Society.", "id": "100753533"}, {"title": "Die gute Einkehr : Auswahl scho\u0308nster Holzschnitte mit Spru\u0308chen und Liedern Ludwig Richter ", "author": "Richter, Ludwig, 1803-1884.", "id": "005722340"}, {"title": "The human figure by John H. Vanderpoel ... ", "author": "Vanderpoel, John H. 1857-1911.", "id": "001989498"}, {"title": "The human figure by John H. Vanderpoel .. ", "author": "Vanderpoel, John Henry, 1857-1911", "id": "008222656"}, {"title": "The human figure by John H. Vanderpoel ... ", "author": "Vanderpoel, John H. 1857-1911.", "id": "001989498"}, {"title": "Japanische Kinderkunst und unser Zeichenunterricht Richard Rothe ", "author": "Rothe, Richard, 1885-", "id": "102652696"}, {"title": "The miracle of Coral Gables by Rex Beach; illustrated by Edward A. Wilson ", "author": "Beach, Rex, 1877-1949.", "id": "101738115"}, {"title": "Perspective; an elementary text book ", "author": "Lubschez, Ben Jehudah, 1881-", "id": "102102183"}, {"title": "Sketching from nature, a practical treatise on the principles of pictorial composition, by F. J. Glass ... ", "author": "Glass, Frederick James, 1881-1930.", "id": "005822043"}]