[{"title": "Le culte du serpent chez les Ngbandi ", "author": "Tanghe, Basiel.", "id": "010387372"}, {"title": "Die religionen der Afrikaner in ihrem zusammenhang mit dem wirtschaftsleben dargestellt von Carl Meinhof ", "author": "Meinhof, Carl, 1857-1944.", "id": "002046109"}, {"title": "Die religionen der Afrikaner in ihrem zusammenhang mit dem wirtschaftsleben dargestellt von Carl Meinhof ", "author": "Meinhof, Carl, 1857-1944.", "id": "002046109"}, {"title": "Die religionen der Afrikaner in ihrem zusammenhang mit dem wirtschaftsleben dargestellt von Carl Meinhof ", "author": "Meinhof, Carl, 1857-1944.", "id": "002046109"}, {"title": "Les statues vivantes ", "author": "Weynants-Ronday, Marie Claire, Mme. 1895-", "id": "001395035"}, {"title": "Les statues vivantes ", "author": "Weynants-Ronday, Marie Claire, Mme. 1895-", "id": "001395035"}, {"title": "Totenglauben und Jenseitsvorstellungen der alten \u00c4gypter; Grundlagen und Entwicklung bis zum Ende des Mittleren Reiches. Mit 5 Abbildungen ", "author": "Kees, Hermann, 1886-", "id": "001940419"}]