[{"title": "Dictionnaire pratique et historique de la musique par Michel Brenet [pseud.] 510 citations musicales.--140 figures ", "author": "Brenet, Michel, 1858-1918.", "id": "001454092"}, {"title": "Grove's dictionary of music and musicians edited by J.A. Fuller Maitland suppl.", "author": "Pratt, Waldo Selden, 1857-1939. Fuller-Maitland, J. A. (John Alexander), 1856-1936. Grove, George, 1820-1900. Boyd, Charles Newell, 1875-1937.", "id": "100145147"}, {"title": "Grove's dictionary of music and musicians edited by J.A. Fuller Maitland v.1", "author": "Pratt, Waldo Selden, 1857-1939. Fuller-Maitland, J. A. (John Alexander), 1856-1936. Grove, George, 1820-1900. Boyd, Charles Newell, 1875-1937.", "id": "100145147"}, {"title": "Grove's dictionary of music and musicians ed. by J. A. Fuller Maitland v.1", "author": "Grove, George, 1820-1900", "id": "101833998"}, {"title": "Grove's dictionary of music and musicians edited by J.A. Fuller Maitland v.2", "author": "Pratt, Waldo Selden, 1857-1939. Fuller-Maitland, J. A. (John Alexander), 1856-1936. Grove, George, 1820-1900. Boyd, Charles Newell, 1875-1937.", "id": "100145147"}, {"title": "Grove's dictionary of music and musicians ed. by J. A. Fuller Maitland v.2", "author": "Grove, George, 1820-1900", "id": "101833998"}, {"title": "Grove's dictionary of music and musicians edited by J.A. Fuller Maitland v.3", "author": "Pratt, Waldo Selden, 1857-1939. Fuller-Maitland, J. A. (John Alexander), 1856-1936. Grove, George, 1820-1900. Boyd, Charles Newell, 1875-1937.", "id": "100145147"}, {"title": "Grove's dictionary of music and musicians ed. by J. A. Fuller Maitland v.3", "author": "Grove, George, 1820-1900", "id": "101833998"}, {"title": "Grove's dictionary of music and musicians edited by J.A. Fuller Maitland v.4", "author": "Pratt, Waldo Selden, 1857-1939. Fuller-Maitland, J. A. (John Alexander), 1856-1936. Grove, George, 1820-1900. Boyd, Charles Newell, 1875-1937.", "id": "100145147"}, {"title": "Grove's dictionary of music and musicians ed. by J. A. Fuller Maitland v.4", "author": "Grove, George, 1820-1900", "id": "101833998"}, {"title": "Grove's dictionary of music and musicians edited by J.A. Fuller Maitland v.5", "author": "Pratt, Waldo Selden, 1857-1939. Fuller-Maitland, J. A. (John Alexander), 1856-1936. Grove, George, 1820-1900. Boyd, Charles Newell, 1875-1937.", "id": "100145147"}, {"title": "Grove's dictionary of music and musicians ed. by J. A. Fuller Maitland v.5", "author": "Grove, George, 1820-1900", "id": "101833998"}, {"title": "Grove's dictionary of music and musicians ed. by J. A. Fuller Maitland v.6", "author": "Grove, George, 1820-1900", "id": "101833998"}, {"title": "Das Neue Musiklexikon : nach dem Dictionary of modern music and musicians hrsg. von A. Eaglefield-Hull ; \u00fcbersetzt und bearbeitet von Alfred Einstein ", "author": "Einstein, Alfred, 1880-1952. Hull, A. Eaglefield (Arthur Eaglefield), 1876-1928.", "id": "001977233"}]