[{"title": "P\u0159ehled rozhodnut\u00ed ze v\u0161ech obor\u016f pr\u00e1vn\u00edch. P\u0159\u00edloha \"\u010casopisu pro pr\u00e1vn\u00ed a st\u00e1tn\u00ed v\u011bdu.\" cislo 3/6 1923/1926", "author": "Fi\u0161er, Metod Chytil, Alois", "id": "010427598"}, {"title": "Rozhodnuti\u0301 ve ve\u030ccech trestni\u0301ch v.008 yr.1926", "author": "Czechoslovakia. Nejvys\u030cs\u030ci\u0301 soud.", "id": "100184412"}, {"title": "Sammlung der rechtss\u00e4tze der obersten gerichte Zivilrechtssachen Bd. 2 1926", "author": "Czechoslovakia. Courts", "id": "010427597"}, {"title": "Sammlung der rechtss\u00e4tze der obersten gerichte Zivilrechtssachen Bd. 3 1926", "author": "Czechoslovakia. Courts", "id": "010427597"}, {"title": "Sammlung der rechtss\u00e4tze der obersten gerichte Verwaltungssachen Bd. 3 1926", "author": "Czechoslovakia. Courts", "id": "010427597"}, {"title": "Sb\u00edrka z\u00e1kon\u016f a na\u0159\u00edzen\u00ed st\u00e1tu \u010deskoslovensk\u00e9ho 1926", "author": "Czechoslovakia.", "id": "012504661"}]