[{"title": "Atenei\u0306 no.1-3 1924-1926", "author": "", "id": "008563196"}, {"title": "Contemporary Russian literature, 1881-1925 ", "author": "Mirsky, D. S., Prince, 1890-1939.", "id": "001055046"}, {"title": "Contemporary Russian literature, 1881-1925 ", "author": "Mirsky, D. S., Prince, 1890-1939.", "id": "001055046"}, {"title": "Essays on Russian novelists ", "author": "Phelps, William Lyon, 1865-1943.", "id": "102090985"}, {"title": "Ge\u012dllustreerde geschiedenis der russische letterkunde ", "author": "Wijk, Nicolaas van, 1880-1941.", "id": "001849120"}, {"title": "Pami\u0361ati Nestora Aleksandrovicha Kotli\u0361arevskogo, 1863-1925 ", "author": "", "id": "001731515"}]