[{"title": "August der Starke von Paul Haake ", "author": "Haake, Paul, 1873-", "id": "000462620"}, {"title": "Der bayer. Landtag 1831; ein Wendepunkt in der Regierung Ludwigs I. ... ", "author": "G\u00f6lz, Wilhelmine, 1897-", "id": "000569285"}, {"title": "Bayerische Verfassungska\u0308mpfe von der Sta\u0308ndekammer zum Landtag ", "author": "Franz, Eugen, 1892-", "id": "005973857"}, {"title": "Die bayerischen ortsnamen als grundlage der siedelungsgeschichte von B. Eberl v. 1", "author": "Eberl, Bartholom\u00e4us.", "id": "007916185"}, {"title": "Die bayerischen ortsnamen als grundlage der siedelungsgeschichte von B. Eberl v. 2", "author": "Eberl, Bartholom\u00e4us.", "id": "007916185"}, {"title": "Bayern und das Preussische Unionsprojekt von M. Doeberl ", "author": "Doeberl, M. 1861-1928.", "id": "005970359"}, {"title": "Bayern und Deutschland v.1", "author": "Doeberl, M. 1861-1928", "id": "000569158"}, {"title": "Bayern und Deutschland v.1", "author": "Doeberl, M. 1861-1928", "id": "000569158"}, {"title": "Bayern und Deutschland c.1 v.2/3", "author": "Doeberl, M. 1861-1928", "id": "000569158"}, {"title": "Bayern und Deutschland v.2", "author": "Doeberl, M. 1861-1928", "id": "000569158"}, {"title": "Bayern und Deutschland v.2", "author": "Doeberl, M. 1861-1928", "id": "000569158"}, {"title": "Bayern und Deutschland v.3", "author": "Doeberl, M. 1861-1928", "id": "000569158"}, {"title": "Bayern und Deutschland v.3", "author": "Doeberl, M. 1861-1928", "id": "000569158"}, {"title": "Das buch vom Rhein : eine schilderung des Rheinstromes und seiner ufer von den quellen bis zum meere unter besonderer beru\u0308cksichtigung seiner 2000 ja\u0308hrigen geschichte von Georg Ho\u0308lscher ", "author": "Ho\u0308lscher, Georg, 1863-1928.", "id": "008989792"}, {"title": "Die deutsche Hanse ... Dargestellt von Konrad Mass ", "author": "Mass, Konrad, 1867-1950.", "id": "010369174"}, {"title": "Der Deutsche und das Rheingebiet von G. Aubin ... [et al.] ; mit einer Sprachenkarte von Elsass-Lothringen, einer Karte der besetzten Gebiete, u\u0308berlassen vom Preussischen Statistischen Landesamt, und mit 35 anderen Karten und Skizzen sowie 17 Abbildungen ", "author": "Aubin, Gustav, 1881-1938. Ficker, Johannes, 1861-1944. Universita\u0308t Halle-Wittenberg.", "id": "006252619"}, {"title": "Elsass-Lothringisches Jahrbuch v.5 1926", "author": "Wissenschaftliches Institut der Elsass-Lotheringer im Reich, Frankfurt am Main.", "id": "000499665"}, {"title": "Die Entstehung der altjulichschen Stadte ", "author": "Koof, Peter, 1897-1961.", "id": "010297077"}, {"title": "Forschungen zur brandenburgischen und preussischen Geschichte v. 38 1926", "author": "Preussische Historische Kommission. Verein f\u00fcr Geschichte der Mark Brandenburg.", "id": "007858928"}, {"title": "Grossherzog Friedrich I. von Baden; ein f\u00fcrstlicher Nationalpolitiker im Zeitalter der Reichsgr\u00fcndung ", "author": "Oncken, Hermann, 1869-1945.", "id": "011809176"}, {"title": "Die Grossm\u00e4chte und die Rheinfrage in den letzten Jahrhunderten von Helmut G\u00f6ring ", "author": "G\u00f6ring, Helmut, 1894-", "id": "010109506"}, {"title": "Hansische Geschichtsbl\u00e4tter v.50-51 1925-1926", "author": "Hansischer Geschichtsverein (L\u00fcbeck, Germany)", "id": "000503583"}, {"title": "Hansische Geschichtsbl\u00e4tter 1925-26", "author": "Hansischer Geschichtsverein (L\u00fcbeck, Germany)", "id": "000503583"}, {"title": "Histoire de Lorraine ", "author": "Morizet, Georges.", "id": "006526888"}, {"title": "Jahrbuch 1926", "author": "Schleswig-Holsteinische Universit\u00e4tsgesellschaft.", "id": "000541928"}, {"title": "Jena, die universit\u00e4tsstadt herausgegeben vom Verkehrsverein Jena ", "author": "Verkehrsverein Jena.", "id": "000570688"}, {"title": "Der Kampf um den Rhein; das Stromgebiet des Rheins im rahmen der grossen Politik und im wandel der Kriegsgeschichte ", "author": "Stegemann, Hermann, 1870-1945.", "id": "008989754"}, {"title": "K\u00f6nig Ludwig II. und seine welt ", "author": "Wolf, Georg Jacob, 1882-1952.", "id": "002623987"}, {"title": "Leben und arbeit in Bayern herausgegeben von dr. Max Stoll ... unter mitwirkung von dr. Hans Karlinger ... ", "author": "Stoll, Max, 1888-", "id": "006299587"}, {"title": "M. Z. Topographia superioris Saxoni\u00e6, Th\u00fcringi\u00e6, Misni\u00e6, Lusati\u00e6, etc.: das ist, Beschreibung der vorne[mbste]n vnd bekantesten st\u00e4tt vnd pl\u00e4tz in churf\u00fcrstenthum Sachsen, Th\u00fcrigen, Meissen, Ober vnd Nider Laussnitzvnd einverleibten landen; auch in andern zu dem hochl\u00f6blichsten s\u00e4chsischen craisse geh\u00f6rigen f\u00fcrstentumen (ausser Brandenburg vnd Pommeren) graff: vnd herrschafften, etc Franckfurt, M. Merian, 1650 ", "author": "Zeiller, Martin, 1589-1661.", "id": "012202005"}, {"title": "Niedersachsen v.31 1926 Jul-Dec", "author": "", "id": "003836866"}, {"title": "Niedersachsen v.31 1926 Jan-Jun", "author": "", "id": "003836866"}, {"title": "Der politische kampf um die gestaltung des landes Th\u00fcringen; bericht der Sozialdemokratischen landtagsfraktion 1924-1926 ... Hrsg. von der Sozialdemokratischen landtagsfraktion ", "author": "Sozialdemokratische Partei Deutschlands.", "id": "001751609"}, {"title": "Publikationen der Gesellschaft fu\u0308r Rheinische Geschichtskunde yr.1926 v.16 pt.03", "author": "Gesellschaft fu\u0308r Rheinische Geschichtskunde.", "id": "000535955"}, {"title": "The Rhine from the Dutch to the Alsatian frontier : handbook for travellers 1926", "author": "Karl Baedeker (Firm)", "id": "007497299"}, {"title": "Schriften des Vereins fu\u0308r Geschichte des Bodensees und seiner Umgebung no.53-54 1924-1926", "author": "Verein fu\u0308r Geschichte des Bodensees und Seiner Umgebung.", "id": "000677414"}, {"title": "Slesvig paa Fredskonferencen, Januar 1919 - Januar 1920 af Andre\u0301 Tardieu, i samarbejde med Franz v. Jessen ", "author": "Tardieu, Andre\u0301, 1876-1945.", "id": "007555250"}, {"title": "Slesvig-Holstens Historie i Grundrids autoriseret Overs\u00e6ttelse ved Ebba Brandt f. Bartholin ", "author": "Brandt, Otto, 1892-1935.", "id": "005733187"}, {"title": "A wayfarer in Alsace by B. S. Townroe, with an introduction by the Rt. Hon. the Earl of Derby, with 18 illustrations and a map ", "author": "Townroe, Bernard Stephen.", "id": "008007004"}, {"title": "W\u00fcrttembergische Studien : Festschrift zum 70. Geburtstag von Professor Eugen N\u00e4gele [Herausgeber, P. Goessler]. ", "author": "N\u00e4gele, Eugen, 1856- Goessler, Peter, 1872-", "id": "000744210"}, {"title": "Zeitschrift des Harz-Vereins f\u00fcr Geschichte und Alterthumskunde v.56-59 (1923-26)", "author": "Jacobs, Eduard, 1833-1919, Harzverein f\u00fcr Geschichte und Altertumskunde,", "id": "008888382"}]